{
  "url": "https://cookpad.com/jp/recipes/19411740",
  "jsonLd": {
    "@context": "https://schema.org",
    "@type": "Recipe",
    "name": "だしと昆布茶が美味い！特製だしおにぎり！",
    "image": "https://img-global-jp.cpcdn.com/recipes/4514876/1200x630cq80/photo.jpg",
    "url": "https://cookpad.com/jp/recipes/19411740",
    "description": "特製だしの素で、おにぎりが美味い！ 顆粒だしと昆布茶が効いてます！",
    "datePublished": "2017-05-15",
    "dateModified": "2017-05-15",
    "keywords": "ご飯,特製だしの素,焼き海苔,塩,顆粒だしの素,昆布茶,旨み調味料",
    "recipeYield": "1個分",
    "recipeInstructions": [
      {
        "@type": "HowToStep",
        "text": "ラップを広げ、その上に特製だしの素をパラパラと振りかけます。",
        "image": "https://img-global-jp.cpcdn.com/steps/22394690/400x400cq80/photo.jpg"
      },
      {
        "@type": "HowToStep",
        "text": "その上に、熱々のご飯をのせます。",
        "image": "https://img-global-jp.cpcdn.com/steps/22394695/400x400cq80/photo.jpg"
      },
      {
        "@type": "HowToStep",
        "text": "さらにその上から、特製だしの素をほんの少しパラパラとかけます。",
        "image": "https://img-global-jp.cpcdn.com/steps/22394700/400x400cq80/photo.jpg"
      },
      {
        "@type": "HowToStep",
        "text": "ご飯をラップで包んで、ニギニギ、ニギニギ、おにぎりの三角形に握ります。",
        "image": "https://img-global-jp.cpcdn.com/steps/22394704/400x400cq80/photo.jpg"
      },
      {
        "@type": "HowToStep",
        "text": "焼き海苔を、1/3に切って、おにぎりに巻き付けて完成です。",
        "image": "https://img-global-jp.cpcdn.com/steps/22394708/400x400cq80/photo.jpg"
      },
      {
        "@type": "HowToStep",
        "text": "レシピID:19387335\nカリカリベーコン、おにぎり！\nも見てね！",
        "image": "https://img-global-jp.cpcdn.com/steps/22441833/400x400cq80/photo.jpg"
      },
      {
        "@type": "HowToStep",
        "text": "レシピID:19142831  \nひがし〇風ゆでうどん\nも見てね！\nレシピ公開は、ここから始まりました！",
        "image": "https://img-global-jp.cpcdn.com/steps/22441834/400x400cq80/photo.jpg"
      }
    ],
    "recipeIngredient": [
      "ご飯 120～140g",
      "特製だしの素 少々",
      "焼き海苔 1/3枚",
      "塩 小さじ1",
      "顆粒だしの素 小さじ1",
      "昆布茶 小さじ1",
      "旨み調味料 少々"
    ],
    "author": {
      "@type": "Person",
      "name": "クックまいななパパ",
      "url": "https://cookpad.com/jp/users/40129069"
    },
    "recipeCuisine": "日本語",
    "interactionStatistic": [
      {
        "@type": "InteractionCounter",
        "interactionType": "http://schema.org/BookmarkAction",
        "userInteractionCount": 455
      }
    ]
  },
  "timestamp": "2025-08-08T19:45:42.332Z"
}