{
  "url": "https://cookpad.com/jp/recipes/19168563",
  "jsonLd": {
    "@context": "https://schema.org",
    "@type": "Recipe",
    "name": "☆5分で完成・簡単☆ジャムドレッシング",
    "image": "https://img-global-jp.cpcdn.com/recipes/4433904/1200x630cq80/photo.jpg",
    "url": "https://cookpad.com/jp/recipes/19168563",
    "description": "【カテゴリ掲載★感謝】フルーツジャムがお手軽ドレッシングに！爽やか美味しいサラダ☆マーマレード以外にもアレンジは無限大♪",
    "datePublished": "2017-03-30",
    "dateModified": "2020-02-17",
    "keywords": "オレンジマーマレード,酢,オリーブオイル,塩コショウ,にんにくチューブ,レモン汁,サニーレタス,ベビーリーフ,ミニトマト,松の実orヒマワリの種",
    "recipeYield": "2人分",
    "recipeInstructions": [
      {
        "@type": "HowToStep",
        "text": "オリーブオイルなど全てのドレッシングの材料をボールに混ぜ合わせる。",
        "image": "https://img-global-jp.cpcdn.com/steps/22052874/400x400cq80/photo.jpg"
      },
      {
        "@type": "HowToStep",
        "text": "ミニトマトを4等分に切り、サニーレタス、ベビーリーフ、松の実・ヒマワリの種と並べた上にドレッシングをかけて完成！",
        "image": "https://img-global-jp.cpcdn.com/steps/22052902/400x400cq80/photo.jpg"
      },
      {
        "@type": "HowToStep",
        "text": "例えば、サラダチキンや鶏ハム、玉ねぎ・人参などと合わせても美味ですよ☆",
        "image": "https://img-global-jp.cpcdn.com/steps/22052931/400x400cq80/photo.jpg"
      },
      {
        "@type": "HowToStep",
        "text": "☆マーマレードを使ってスペアリブはいかが？\nレシピID:19168182",
        "image": "https://img-global-jp.cpcdn.com/steps/22055517/400x400cq80/photo.jpg"
      },
      {
        "@type": "HowToStep",
        "text": "☆5分でできるオニオンスープも美味♪\nレシピID：19180254",
        "image": "https://img-global-jp.cpcdn.com/steps/22075571/400x400cq80/photo.jpg"
      }
    ],
    "recipeIngredient": [
      "オレンジマーマレード 小さじ2",
      "酢 小さじ2",
      "オリーブオイル 小さじ2",
      "塩コショウ 小さじ1",
      "にんにくチューブ 2cmほど",
      "レモン汁 お好みで",
      "サニーレタス 20g",
      "ベビーリーフ 30g",
      "ミニトマト 4つ",
      "松の実orヒマワリの種 お好みで"
    ],
    "author": {
      "@type": "Person",
      "name": "NoBPooh",
      "url": "https://cookpad.com/jp/users/40155292"
    },
    "recipeCuisine": "日本語",
    "interactionStatistic": [
      {
        "@type": "InteractionCounter",
        "interactionType": "http://schema.org/BookmarkAction",
        "userInteractionCount": 210
      }
    ],
    "comment": [
      {
        "@type": "Comment",
        "name": "Cooksnap",
        "author": {
          "@type": "Person",
          "name": "お料理苦手ママン",
          "url": "https://cookpad.com/jp/users/40559120"
        },
        "datePublished": "2025-06-20",
        "text": "おしゃれなサラダが出来上がりました〜！\nお店みたいです。\nありがとうございます"
      },
      {
        "@type": "Comment",
        "name": "Cooksnap",
        "author": {
          "@type": "Person",
          "name": "もんしゅしゅ",
          "url": "https://cookpad.com/jp/users/40133526"
        },
        "datePublished": "2021-06-13",
        "text": "ジャムとお野菜って合いますね♡美味しくお洒落で素敵♪感謝デス❤"
      },
      {
        "@type": "Comment",
        "name": "Cooksnap",
        "author": {
          "@type": "Person",
          "name": "ソネチコ",
          "url": "https://cookpad.com/jp/users/40046224"
        },
        "datePublished": "2021-04-14",
        "text": "柚子茶で。爽やか〜〜カニカマによくあいました!"
      },
      {
        "@type": "Comment",
        "name": "Cooksnap",
        "author": {
          "@type": "Person",
          "name": "yukiest",
          "url": "https://cookpad.com/jp/users/40908503"
        },
        "datePublished": "2020-02-17",
        "text": "余っていたいちじくジャム救済に。めっちゃおいしくてどハマリ中です"
      },
      {
        "@type": "Comment",
        "name": "Cooksnap",
        "author": {
          "@type": "Person",
          "name": "papikun",
          "url": "https://cookpad.com/jp/users/40032573"
        },
        "datePublished": "2020-01-11",
        "text": "マーマレードジャムの消費にと作ったら、市販！？と大好評❤︎"
      },
      {
        "@type": "Comment",
        "name": "Cooksnap",
        "author": {
          "@type": "Person",
          "name": "megshio",
          "url": "https://cookpad.com/jp/users/40509379"
        },
        "datePublished": "2019-07-15",
        "text": "サラダパスタにして食べました！パスタにも合います。"
      }
    ],
    "commentCount": 9
  },
  "timestamp": "2025-08-08T19:54:34.789Z"
}