[
  {
    "@context": "https://schema.org/",
    "@type": "Recipe",
    "name": "定番・豚肉のしょうが焼き【黄金比率の味つけ】",
    "image": [
      "https://www.kikkoman.co.jp/homecook/assets/img/00004693.jpg"
    ],
    "author": {
      "@type": "Person",
      "name": "キッコーマン"
    },
    "description": "「定番・豚肉のしょうが焼き【黄金比率の味つけ】」のレシピをご紹介しています。料理レシピ満載のホームクッキングでは、今日のレシピ・献立、旬の食材のレシピ、簡単お弁当レシピ、朝食レシピなどをご紹介しています。料理レシピ検索では、食材別、キーワードなどからお好みレシピを簡単に検索いただけます。",
    "totalTime": "PT20M",
    "keywords": "23年春夏  減塩メニューに起用　キッコーマン病院監修　ゆる減塩",
    "recipeYield": "2人分",
    "nutrition": {
      "@type": "NutritionInformation",
      "calories": "339kcal"
    },
    "recipeIngredient": [
      "豚ロース肉 ２００ｇ",
      "キャベツ ２枚",
      "サラダ油 小さじ２",
      "マンジョウ国産米こだわり仕込み料理の清酒 小さじ１",
      "キッコーマン特選丸大豆しょうゆ 小さじ１",
      "マンジョウ国産米こだわり仕込み料理の清酒 大さじ１",
      "マンジョウ米麹こだわり仕込み本みりん 大さじ１",
      "キッコーマン特選丸大豆しょうゆ 小さじ２",
      "しょうが １片分"
    ],
    "recipeInstructions": [
      {
        "@type": "HowToStep",
        "text": "キャベツはせん切りにする。"
      },
      {
        "@type": "HowToStep",
        "text": "豚肉は筋を切り、（Ａ）で下味をつける。"
      },
      {
        "@type": "HowToStep",
        "text": "フライパンにサラダ油を強火で熱し、豚肉の両面をこんがりと香ばしく焼き、余分な油をキッチンペーパーでふき取る。"
      },
      {
        "@type": "HowToStep",
        "text": "（Ｂ）のたれの材料を順に入れて混ぜ、全体をよく絡める。キャベツとともに盛りつける。"
      }
    ]
  }
]